{
  "abilityScores": [
    {
      "name": "str",
      "value": 10
    },
    {
      "name": "dex",
      "value": 15
    },
    {
      "name": "con",
      "value": 16
    },
    {
      "name": "int",
      "value": 12
    },
    {
      "name": "wis",
      "value": 13
    },
    {
      "name": "cha",
      "value": 15
    }
  ],
  "actions": [
    {
      "description": "Melee Weapon Attack: +5 to hit, reach 5 ft., one creature. Hit: 4 (1d4 + 2) piercing damage plus 14 (4d6) poison damage.",
      "name": "Snake Hair",
      "sortOrder": 0,
      "steps": [
        {
          "attack": {
            "ability": "dex",
            "crit": 20,
            "damageRolls": [
              {
                "abilityName": "dex",
                "dice": "1d4",
                "type": "Piercing"
              },
              {
                "dice": "4d6",
                "type": "Poison"
              }
            ],
            "isProficient": true,
            "isRanged": false,
            "name": "Snake Hair",
            "rollsAttack": true,
            "savingThrow": {
            }
          },
          "journalCommand": {
          },
          "skillCheck": {
          },
          "type": "custom-attack"
        }
      ]
    },
    {
      "description": "Melee Weapon Attack: +5 to hit, reach 5 ft., one target. Hit: 5 (1d6 + 2) piercing damage.",
      "name": "Shortsword",
      "sortOrder": 1,
      "steps": [
        {
          "attack": {
            "ability": "dex",
            "crit": 20,
            "damageRolls": [
              {
                "abilityName": "dex",
                "dice": "1d6",
                "type": "Piercing"
              }
            ],
            "isProficient": true,
            "isRanged": false,
            "name": "Shortsword",
            "rollsAttack": true
          },
          "type": "custom-attack"
        }
      ]
    },
    {
      "description": "Ranged Weapon Attack: +5 to hit, range 150/600 ft., one target. Hit: 6 (1d8 + 2) piercing damage plus 7 (2d6) poison damage.",
      "name": "Longbow",
      "sortOrder": 2,
      "steps": [
        {
          "attack": {
            "ability": "dex",
            "crit": 20,
            "damageRolls": [
              {
                "abilityName": "dex",
                "dice": "1d8",
                "type": "Piercing"
              },
              {
                "dice": "2d6",
                "type": "Poison"
              }
            ],
            "isProficient": true,
            "isRanged": true,
            "longRange": 600,
            "name": "Longbow",
            "range": 150,
            "rollsAttack": true,
            "savingThrow": {
            }
          },
          "journalCommand": {
          },
          "skillCheck": {
          },
          "type": "custom-attack"
        }
      ]
    },
    {
      "description": "When a creature that can see the medusa's eyes starts its turn within 30 feet of the medusa, the medusa can force it to make a DC 14 Constitution saving throw if the medusa isn't incapacitated and can see the creature. If the saving throw fails by 5 or more, the creature is instantly petrified. Otherwise, a creature that fails the save begins to turn to stone and is restrained. The restrained creature must repeat the saving throw at the end of its next turn, becoming petrified on a failure or ending the effect on a success. The petrification lasts until the creature is freed by the greater restoration spell or other magic.\n   Unless surprised, a creature can avert its eyes to avoid the saving throw at the start of its turn. If the creature does so, it can't see the medusa until the start of its next turn, when it can avert its eyes again. If the creature looks at the medusa in the meantime, it must immediately make the save.\n   If the medusa sees itself reflected on a polished surface within 30 feet of it and in an area of bright light, the medusa is, due to its curse, affected by its own gaze.",
      "name": "Petrifying Glaze",
      "sortOrder": 3,
      "steps": [
        {
          "attack": {
            "crit": 20,
            "isProficient": true,
            "isRanged": false,
            "name": "Petrifying Glaze",
            "rollsAttack": false,
            "savingThrow": {
              "abilityName": "con",
              "difficultyClass": 14
            }
          },
          "type": "custom-attack"
        }
      ]
    }
  ],
  "alignment": "Lawful Evil",
  "armorClass": 15,
  "armorType": "Natural Armor",
  "challengeRating": "6",
  "classes": [
    {
      "class": "Monster",
      "level": 1
    }
  ],
  "currentHp": 127,
  "exp": 2300,
  "hitDice": "17d8+51",
  "imageUri": "https://cdn.alchemyrpg.com/app-assets/monstrosity-token.svg",
  "initiativeBonus": 0,
  "isNPC": true,
  "maxHp": 127,
  "movementModes": [
    {
      "distance": 30,
      "mode": "Walking"
    }
  ],
  "name": "Medusa",
  "proficiencies": [
    {
      "name": "Common",
      "type": "language"
    }
  ],
  "proficiencyBonus": 3,
  "race": "NPC",
  "senses": [
    {
      "distance": 60,
      "name": "Darkvision"
    }
  ],
  "size": "Medium",
  "skills": [
    {
      "abilityName": "dex",
      "name": "Acrobatics",
      "proficient": false
    },
    {
      "abilityName": "wis",
      "name": "Animal Handling",
      "proficient": false
    },
    {
      "abilityName": "int",
      "name": "Arcana",
      "proficient": false
    },
    {
      "abilityName": "str",
      "name": "Athletics",
      "proficient": false
    },
    {
      "abilityName": "cha",
      "name": "Deception",
      "proficient": true
    },
    {
      "abilityName": "int",
      "name": "History",
      "proficient": false
    },
    {
      "abilityName": "wis",
      "name": "Insight",
      "proficient": true
    },
    {
      "abilityName": "cha",
      "name": "Intimidation",
      "proficient": false
    },
    {
      "abilityName": "int",
      "name": "Investigation",
      "proficient": false
    },
    {
      "abilityName": "wis",
      "name": "Medicine",
      "proficient": false
    },
    {
      "abilityName": "int",
      "name": "Nature",
      "proficient": false
    },
    {
      "abilityName": "wis",
      "name": "Perception",
      "proficient": true
    },
    {
      "abilityName": "cha",
      "name": "Performance",
      "proficient": false
    },
    {
      "abilityName": "cha",
      "name": "Persuasion",
      "proficient": false
    },
    {
      "abilityName": "int",
      "name": "Religion",
      "proficient": false
    },
    {
      "abilityName": "dex",
      "name": "Sleight of Hand",
      "proficient": false
    },
    {
      "abilityName": "dex",
      "name": "Stealth",
      "proficient": true
    },
    {
      "abilityName": "wis",
      "name": "Survival",
      "proficient": false
    }
  ],
  "speed": 30,
  "systemKey": "5e",
  "textBlocks": [
    {
      "title": "Class Features"
    },
    {
      "title": "Racial Traits"
    },
    {
      "title": "Feats"
    },
    {
      "textBlocks": [
        {
        },
        {
        }
      ],
      "title": "Background"
    },
    {
      "textBlocks": [
        {
          "title": "Personality Traits"
        },
        {
          "title": "Ideals"
        },
        {
          "title": "Bonds"
        },
        {
          "title": "Flaws"
        }
      ],
      "title": "Characteristics"
    },
    {
      "textBlocks": [
        {
        }
      ],
      "title": "Appearance"
    },
    {
      "title": "Organizations"
    },
    {
      "title": "Allies"
    },
    {
      "title": "Enemies"
    },
    {
      "textBlocks": [
        {
        }
      ],
      "title": "Backstory"
    },
    {
      "textBlocks": [
        {
        }
      ],
      "title": "Other"
    },
    {
      "textBlocks": [
        {
          "body": "The medusa makes either three melee attacks—one with its snake hair and two with its shortsword—or two ranged attacks with its longbow.",
          "title": "Multiattack"
        }
      ],
      "title": "Abilities"
    }
  ],
  "trackers": [
    {
      "color": "Yellow",
      "max": 355000,
      "name": "XP",
      "type": "Bar",
      "value": 2300
    },
    {
      "color": "Green",
      "max": 127,
      "name": "HP",
      "type": "Bar",
      "value": 127
    }
  ],
  "type": "Monstrosity"
}